Metadata-Version: 1.0
Name: jsonbin
Version: 1.0.0
Summary: A python library for https://jsonbin.marcusweinberger.repl.co/
Home-page: https://github.com/AgeOfMarcus/jsonbin
Author: AgeOfMarcus
Author-email: marcus@marcusweinberger.com
License: UNKNOWN
Platform: UNKNOWN
